semidbm/__init__.py
semidbm/compat.py
semidbm/db.py
semidbm/exceptions.py
semidbm/win32.py
semidbm/loaders/__init__.py
semidbm/loaders/mmapload.py
semidbm/loaders/simpleload.py
semidbm-0.5.1.dist-info/DESCRIPTION.rst
semidbm-0.5.1.dist-info/METADATA
semidbm-0.5.1.dist-info/metadata.json
semidbm-0.5.1.dist-info/RECORD
semidbm-0.5.1.dist-info/top_level.txt
semidbm-0.5.1.dist-info/WHEEL
