Metadata-Version: 1.0
Name: semidbm
Version: 0.5.1
Summary: Cross platform (fast) DBM interface in python
Home-page: https://github.com/jamesls/semidbm
Author: James Saryerwinnie
Author-email: js@jamesls.com
License: BSD
Keywords: semidbm
Platform: UNKNOWN
Classifier: Development Status :: 4 - Beta
Classifier: Programming Language :: Python :: 2.6
Classifier: Programming Language :: Python :: 2.7
Classifier: Programming Language :: Python :: 3.3
Classifier: Programming Language :: Python :: 3.4
Classifier: Programming Language :: Python :: Implementation :: CPython
Classifier: Programming Language :: Python :: Implementation :: PyPy
Classifier: Programming Language :: Python :: Implementation :: Jython
Classifier: License :: OSI Approved :: BSD License
